{"name": "Qayamat Se Qayamat Tak", "director": ["Mansoor Khan"], "country": "India", "language": ["Hindi", "Urdu"], "poster_image_url": "https://m.media-amazon.com/images/M/MV5BZDAwM2E2YmEtN2I3Zi00NmY5LTkxNTAtODVmNmM4MmY2YTFjXkEyXkFqcGdeQXVyODE5NzE3OTE@._V1_UY268_CR1,0,182,268_AL__QL50.jpg", "bio": "A young man and young woman fall in love against their feuding fathers' wishes in this version of 'Romeo and Juliet' set in contemporary India.", "runtime": [162, "mins"], "genre": ["Romance", "Musical", "Drama"], "cast": [{"imbd_actor_id": "nm0451148", "name": "Aamir Khan"}, {"imbd_actor_id": "nm0004487", "name": "Juhi Chawla"}, {"imbd_actor_id": "nm0438474", "name": "Goga Kapoor"}, {"imbd_actor_id": "nm0846681", "name": "Dalip Tahil"}, {"imbd_actor_id": "nm1090174", "name": "Ravindra Kapoor"}, {"imbd_actor_id": "nm0788861", "name": "Asha Sharma"}, {"imbd_actor_id": "nm0622186", "name": "Alok Nath"}, {"imbd_actor_id": "nm0958861", "name": "Raj Zutshi"}, {"imbd_actor_id": "nm1617755", "name": "Shehnaz Kudia"}, {"imbd_actor_id": "nm1401801", "name": "Charushila"}, {"imbd_actor_id": "nm0066455", "name": "Beena Banerjee"}, {"imbd_actor_id": "nm0481363", "name": "Reema Lagoo"}, {"imbd_actor_id": "nm0856900", "name": "Nandita Thakur"}, {"imbd_actor_id": "nm0451156", "name": "Ahmed Khan"}, {"imbd_actor_id": "nm1019296", "name": "Arjun"}, {"imbd_actor_id": "nm0882892", "name": "Ajit Vachani"}, {"imbd_actor_id": "nm0664109", "name": "Yunus Parvez"}, {"imbd_actor_id": "nm0451864", "name": "Viju Khote"}, {"imbd_actor_id": "nm2136994", "name": "Babbanlal Yadav"}, {"imbd_actor_id": "nm1217219", "name": "Arun Mathur"}, {"imbd_actor_id": "nm1403762", "name": "Seema Vaz"}, {"imbd_actor_id": "nm0611480", "name": "Mukesh"}, {"imbd_actor_id": "nm1185344", "name": "Shehzad Khan"}, {"imbd_actor_id": "nm0221218", "name": "Makrand Deshpande"}, {"imbd_actor_id": "nm1244971", "name": "Yatin Karyekar"}, {"imbd_actor_id": "nm1064300", "name": "Shiva Rindani"}, {"imbd_actor_id": "nm0329702", "name": "Brij Gopal"}, {"imbd_actor_id": "nm0882288", "name": "Usha"}, {"imbd_actor_id": "nm1522170", "name": "Afzal"}, {"imbd_actor_id": "nm0451207", "name": "Faisal Khan"}, {"imbd_actor_id": "nm1493754", "name": "Noora"}, {"imbd_actor_id": "nm0951149", "name": "Yusuf"}, {"imbd_actor_id": "nm1405359", "name": "Imran Khan"}, {"imbd_actor_id": "nm2776297", "name": "Charusheela Sabale"}, {"imbd_actor_id": "nm1548528", "name": "Chhaya"}]}