{"name": "Ishqiya", "director": ["Abhishek Chaubey"], "country": "India", "language": ["Hindi"], "poster_image_url": "https://m.media-amazon.com/images/M/MV5BNTc1Y2EyOWUtNWExMi00OGNkLTkxOGQtNDY0YzYxNTA0OWUxXkEyXkFqcGdeQXVyODE5NzE3OTE@._V1_UY268_CR2,0,182,268_AL__QL50.jpg", "bio": "While on the run from goons, a man and his nephew fall for a kidnapper's seductive widow.", "runtime": [118, "mins"], "genre": ["Romance", "Drama", "Comedy"], "cast": [{"imbd_actor_id": "nm1799038", "name": "Vidya Balan"}, {"imbd_actor_id": "nm0787462", "name": "Naseeruddin Shah"}, {"imbd_actor_id": "nm0451174", "name": "Arshad Warsi"}, {"imbd_actor_id": "nm1426805", "name": "Salman Shahid"}, {"imbd_actor_id": "nm1300009", "name": "Adil Hussain"}, {"imbd_actor_id": "nm0788903", "name": "Rajesh Sharma"}, {"imbd_actor_id": "nm3612256", "name": "Anupama Kumar"}, {"imbd_actor_id": "nm3769063", "name": "Gauri Mala"}, {"imbd_actor_id": "nm3750320", "name": "Alok Kumar"}, {"imbd_actor_id": "nm3750231", "name": "Anisha Bano"}, {"imbd_actor_id": "nm9241618", "name": "Rakesh Sharma"}, {"imbd_actor_id": "nm1198512", "name": "Jai Singh"}]}