{"name": "Gangs of Wasseypur", "director": ["Anurag Kashyap"], "country": "India", "language": ["Hindi"], "poster_image_url": "https://m.media-amazon.com/images/M/MV5BMTc5NjY4MjUwNF5BMl5BanBnXkFtZTgwODM3NzM5MzE@._V1_UX182_CR0,0,182,268_AL__QL50.jpg", "bio": "A clash between Sultan and Shahid Khan leads to the expulsion of Khan from Wasseypur, and ignites a deadly blood feud spanning three generations.", "runtime": [321, "mins"], "genre": ["Drama", "Crime", "Action"], "cast": [{"imbd_actor_id": "nm0048075", "name": "Manoj Bajpayee"}, {"imbd_actor_id": "nm3190246", "name": "Richa Chadha"}, {"imbd_actor_id": "nm1596350", "name": "Nawazuddin Siddiqui"}, {"imbd_actor_id": "nm0223606", "name": "Tigmanshu Dhulia"}, {"imbd_actor_id": "nm0451239", "name": "Jameel Khan"}, {"imbd_actor_id": "nm0592795", "name": "Piyush Mishra"}, {"imbd_actor_id": "nm4188433", "name": "Jaideep Ahlawat"}, {"imbd_actor_id": "nm4806622", "name": "Huma Qureshi"}, {"imbd_actor_id": "nm5113220", "name": "Zeishan Quadri"}, {"imbd_actor_id": "nm1479650", "name": "Vipin Sharma"}, {"imbd_actor_id": "nm3864624", "name": "Satyakam Anand"}, {"imbd_actor_id": "nm4748818", "name": "Aditya Kumar"}, {"imbd_actor_id": "nm3822770", "name": "Rajkummar Rao"}, {"imbd_actor_id": "nm1277547", "name": "Vineet Kumar Singh"}, {"imbd_actor_id": "nm4435813", "name": "Sankalp Acharekar"}, {"imbd_actor_id": "nm5129212", "name": "Mahesh Balraj"}, {"imbd_actor_id": "nm2535507", "name": "Mukesh Chhabra"}, {"imbd_actor_id": "nm7436747", "name": "Shreedhar Dubey"}, {"imbd_actor_id": "nm4839358", "name": "Anurita Jha"}, {"imbd_actor_id": "nm1390115", "name": "Harish Khanna"}, {"imbd_actor_id": "nm2715305", "name": "Murari Kumar"}, {"imbd_actor_id": "nm6763126", "name": "Faisal Malik"}, {"imbd_actor_id": "nm1221483", "name": "Pramod Pathak"}, {"imbd_actor_id": "nm3771295", "name": "Vijesh Rajan"}, {"imbd_actor_id": "nm1032614", "name": "Reema Sen"}, {"imbd_actor_id": "nm6422090", "name": "Rajesh Kumar Sharma"}, {"imbd_actor_id": "nm1004985", "name": "Yashpal Sharma"}, {"imbd_actor_id": "nm7372243", "name": "Pawan Singh"}, {"imbd_actor_id": "nm7916099", "name": "Sanjay Singh"}, {"imbd_actor_id": "nm4518724", "name": "Akash Sinha"}, {"imbd_actor_id": "nm3720865", "name": "Suhas Sirsat"}, {"imbd_actor_id": "nm2690647", "name": "Pankaj Tripathi"}, {"imbd_actor_id": "nm6451984", "name": "Jack Wayne"}, {"imbd_actor_id": "nm4731845", "name": "Rohit Pandey"}, {"imbd_actor_id": "nm1019127", "name": "Sanjeeva Vatsa"}]}