{"name": "Parmanu: The Story of Pokhran", "director": ["Abhishek Sharma"], "country": "India", "language": ["Hindi"], "poster_image_url": "https://m.media-amazon.com/images/M/MV5BMDNjZjkyNjQtNWMyMC00ODA5LTgyODctOGRiOWUwYTAzOWVjXkEyXkFqcGdeQXVyODE5NzE3OTE@._V1_UY268_CR3,0,182,268_AL__QL50.jpg", "bio": "A look at India's second confidential nuclear test series at Pokhran led by Dr. APJ Abdul Kalam, during the time of PM Atal Bihari Vajpayee's tenure.", "runtime": [129, "mins"], "genre": ["History", "Drama", "Action"], "cast": [{"imbd_actor_id": "nm1303433", "name": "John Abraham"}, {"imbd_actor_id": "nm1224082", "name": "Boman Irani"}, {"imbd_actor_id": "nm5069465", "name": "Diana Penty"}, {"imbd_actor_id": "nm7242142", "name": "Anuja Sathe"}, {"imbd_actor_id": "nm1987327", "name": "Vikas Kumar"}, {"imbd_actor_id": "nm0863171", "name": "Yogendra Tikku"}, {"imbd_actor_id": "nm0386943", "name": "Aditya Hitkari"}, {"imbd_actor_id": "nm9869278", "name": "Ajay Shankar"}, {"imbd_actor_id": "nm2586857", "name": "Darshan Pandya"}, {"imbd_actor_id": "nm1204791", "name": "Mark Bennington"}, {"imbd_actor_id": "nm9359858", "name": "Shyam Bhagat"}, {"imbd_actor_id": "nm1882579", "name": "Zachary Coffin"}, {"imbd_actor_id": "nm6554435", "name": "Satinder Singh Gahlot"}, {"imbd_actor_id": "nm9176998", "name": "Tan Raj Ghale"}, {"imbd_actor_id": "nm3912430", "name": "Rohan Khatri"}, {"imbd_actor_id": "nm1521220", "name": "Munna"}, {"imbd_actor_id": "nm8738703", "name": "Arush Nand"}, {"imbd_actor_id": "nm4002386", "name": "Nitesh Nath"}, {"imbd_actor_id": "nm9296774", "name": "Prahlad"}, {"imbd_actor_id": "nm3023631", "name": "Abhiroy Singh"}, {"imbd_actor_id": "nm9359857", "name": "Bhairao Singh"}]}